tinytrie.py
tinytrie-0.1.0.dist-info/licenses/LICENSE
tinytrie-0.1.0.dist-info/METADATA
tinytrie-0.1.0.dist-info/WHEEL
tinytrie-0.1.0.dist-info/top_level.txt
tinytrie-0.1.0.dist-info/RECORD
