Metadata-Version: 2.4
Name: tinytrie
Version: 0.1.0
Summary: A minimal type-safe trie (prefix tree) implementation in Python.
Author-email: Jifeng Wu <jifengwu2k@gmail.com>
License-Expression: MIT
Project-URL: Homepage, https://github.com/jifengwu2k/tinytrie
Project-URL: Bug Tracker, https://github.com/jifengwu2k/tinytrie/issues
Keywords: trie,prefix tree,data structure,python
Classifier: Programming Language :: Python :: 3
Classifier: Operating System :: OS Independent
Requires-Python: >=3.6
License-File: LICENSE
Dynamic: license-file
